distreqx/__init__.py
distreqx/_custom_types.py
distreqx/bijectors/__init__.py
distreqx/bijectors/_bijector.py
distreqx/bijectors/_linear.py
distreqx/bijectors/block.py
distreqx/bijectors/chain.py
distreqx/bijectors/diag_linear.py
distreqx/bijectors/scalar_affine.py
distreqx/bijectors/shift.py
distreqx/bijectors/sigmoid.py
distreqx/bijectors/tanh.py
distreqx/bijectors/triangular_linear.py
distreqx/distributions/__init__.py
distreqx/distributions/_distribution.py
distreqx/distributions/bernoulli.py
distreqx/distributions/categorical.py
distreqx/distributions/independent.py
distreqx/distributions/mixture_same_family.py
distreqx/distributions/mvn_diag.py
distreqx/distributions/mvn_from_bijector.py
distreqx/distributions/mvn_tri.py
distreqx/distributions/normal.py
distreqx/distributions/transformed.py
distreqx/utils/__init__.py
distreqx/utils/math.py
distreqx-0.0.1.dist-info/LICENSE
distreqx-0.0.1.dist-info/METADATA
distreqx-0.0.1.dist-info/WHEEL
distreqx-0.0.1.dist-info/top_level.txt
distreqx-0.0.1.dist-info/RECORD
