Metadata-Version: 2.1
Name: distreqx
Version: 0.0.1
Summary: Lightweight JAX library of probability distributions and bijectors.
Author-email: Owen Lockwood <owen_jax@outlook.com>
License: Apache License
Project-URL: repository, https://github.com/lockwo/distreqx
Keywords: jax,probability,distributions,equinox,machine-learning
Classifier: Development Status :: 3 - Alpha
Classifier: Intended Audience :: Developers
Classifier: Intended Audience :: Financial and Insurance Industry
Classifier: Intended Audience :: Information Technology
Classifier: Intended Audience :: Science/Research
Classifier: License :: OSI Approved :: Apache Software License
Classifier: Natural Language :: English
Classifier: Programming Language :: Python :: 3
Classifier: Topic :: Scientific/Engineering :: Artificial Intelligence
Classifier: Topic :: Scientific/Engineering :: Information Analysis
Classifier: Topic :: Scientific/Engineering :: Mathematics
Classifier: Topic :: Scientific/Engineering :: Physics
Classifier: Topic :: Software Development :: Libraries :: Python Modules
Requires-Python: >=3.9
License-File: LICENSE
Requires-Dist: jax >=0.4.11
Requires-Dist: jaxtyping >=0.2.20
Requires-Dist: equinox >=0.11.0
